__init__.py
serbia_zip_codes.py
data/db.json
serbia_zip_codes-1.0.0.dist-info/LICENSE
serbia_zip_codes-1.0.0.dist-info/METADATA
serbia_zip_codes-1.0.0.dist-info/WHEEL
serbia_zip_codes-1.0.0.dist-info/top_level.txt
serbia_zip_codes-1.0.0.dist-info/RECORD
