Metadata-Version: 2.1
Name: serbia-zip-codes
Version: 1.0.0
Summary: Easy access to Serbia zip codes. You can search zip code by city, or city by zip code
Home-page: https://github.com/nebjak/serbia-zip-codes-py
Author: Nebojsa Jakovljevic
Author-email: nebojsa@nebjak.net
License: MIT License
Keywords: serbia zipcode postcode
Platform: UNKNOWN
Classifier: Programming Language :: Python :: 3
Classifier: Programming Language :: Python :: 3.5
Classifier: Programming Language :: Python :: 3.6
Classifier: Programming Language :: Python :: 3.7
Classifier: Programming Language :: Python :: 3.8
Classifier: License :: OSI Approved :: MIT License
Classifier: Operating System :: OS Independent
Requires-Python: >=3.6
